MANIFEST.in
README.md
VERSION
setup.py
hitchbuildpg/__init__.py
hitchbuildpg/app.py
hitchbuildpg/databuild.py
hitchbuildpg/datafiles.py
hitchbuildpg/server.py
hitchbuildpg/utils.py
hitchbuildpg.egg-info/PKG-INFO
hitchbuildpg.egg-info/SOURCES.txt
hitchbuildpg.egg-info/dependency_links.txt
hitchbuildpg.egg-info/not-zip-safe
hitchbuildpg.egg-info/requires.txt
hitchbuildpg.egg-info/top_level.txt